wechaty_puppet_mock/__init__.py
wechaty_puppet_mock/config.py
wechaty_puppet_mock/exceptions.py
wechaty_puppet_mock/puppet_mock.py
wechaty_puppet_mock/version.py
wechaty_puppet_mock/mock/__init__.py
wechaty_puppet_mock/mock/accessory.py
wechaty_puppet_mock/mock/environment.py
wechaty_puppet_mock/mock/mocker.py
wechaty_puppet_mock/mock/user/__init__.py
wechaty_puppet_mock/mock/user/contact_mock.py
wechaty_puppet_mock/mock/user/message_contact.py
wechaty_puppet_mock/mock/user/room_mock.py
wechaty_puppet_mock-0.0.1.dist-info/LICENSE
wechaty_puppet_mock-0.0.1.dist-info/METADATA
wechaty_puppet_mock-0.0.1.dist-info/NOTICE
wechaty_puppet_mock-0.0.1.dist-info/WHEEL
wechaty_puppet_mock-0.0.1.dist-info/top_level.txt
wechaty_puppet_mock-0.0.1.dist-info/RECORD
